five.globalrequest-99.0-py2.7-nspkg.pth
five/globalrequest/__init__.py
five/globalrequest/configure.zcml
five.globalrequest-99.0.dist-info/DESCRIPTION.rst
five.globalrequest-99.0.dist-info/METADATA
five.globalrequest-99.0.dist-info/RECORD
five.globalrequest-99.0.dist-info/WHEEL
five.globalrequest-99.0.dist-info/metadata.json
five.globalrequest-99.0.dist-info/namespace_packages.txt
five.globalrequest-99.0.dist-info/top_level.txt
