Metadata-Version: 2.0
Name: five.globalrequest
Version: 99.0
Summary: DEPRECATED: Zope integration for zope.globalrequest
Home-page: https://github.com/zopefoundation/five.globalrequest
Author: Zope Foundation and Contributors
Author-email: zope-dev@zope.org
License: ZPL
Keywords: zope global request
Platform: UNKNOWN
Classifier: Framework :: Plone
Classifier: Programming Language :: Python
Classifier: Development Status :: 7 - Inactive
Requires-Dist: setuptools
Requires-Dist: Zope (>=4.0a3)
